aesoppy/__init__.py
aesoppy/aesop/__init__.py
aesoppy/aesop/common.py
aesoppy/aesop/debt.py
aesoppy/aesop/dividend_coverage.py
aesoppy/aesop/dividend_growth.py
aesoppy/aesop/dividend_yield_theory.py
aesoppy/aesop/growth.py
aesoppy/aesop/margins.py
aesoppy/aesop/market_valuation.py
aesoppy/aesop/owners.py
aesoppy/gurufocus/__init__.py
aesoppy/gurufocus/dividend.py
aesoppy/gurufocus/financials.py
aesoppy/gurufocus/price.py
h2w_aesoppy-1.2.0.dist-info/LICENSE.txt
h2w_aesoppy-1.2.0.dist-info/METADATA
h2w_aesoppy-1.2.0.dist-info/WHEEL
h2w_aesoppy-1.2.0.dist-info/top_level.txt
h2w_aesoppy-1.2.0.dist-info/RECORD
