Metadata-Version: 2.2
Name: h2w-aesoppy
Version: 1.2.0
Summary: Python Library for Data Wrangling and API Interactions on Stock Market Data
Author: Harvey Wargo
License: MIT License
Project-URL: Homepage, https://github.com/harveywargo2/h2w-aesoppy
Keywords: Stock,GuruFocus,Stock Data,Dividends
Classifier: Programming Language :: Python
Classifier: Programming Language :: Python :: 3
Requires-Python: >=3.9
License-File: LICENSE.txt
Requires-Dist: requests
Requires-Dist: pandas
Requires-Dist: datetime
